{"bioguide_id":"N000147","birthday":"1937-06-13","chamber":"house","contact_form":"http://www.norton.house.gov/forms/contact.html","crp_id":"N00001692","district":0,"facebook_id":"61731840657","fax":"202-225-3002","fec_ids":["H0DC00058"],"first_name":"Eleanor","gender":"F","govtrack_id":"400295","in_office":true,"last_name":"Norton","middle_name":"Holmes","name_suffix":null,"nickname":null,"office":"2136 Rayburn House Office Building","party":"D","phone":"202-225-8050","state":"DC","state_name":"District of Columbia","thomas_id":"00868","title":"Del","twitter_id":"EleanorNorton","votesmart_id":775,"website":"http://www.house.gov/norton","youtube_id":"EleanorHNorton","twitter_id_number":23600262,"twitter_scrape":{"default_profile_image":false,"created_at":"Tue Mar 10 14:47:46 +0000 2009","name":"Eleanor H. Norton","favourites_count":1,"profile_background_image_url":"http://a0.twimg.com/profile_background_images/266506620/twitpic8.jpg","contributors_enabled":false,"profile_link_color":"D6930D","verified":true,"id":23600262,"id_str":"23600262","status":{"in_reply_to_status_id_str":null,"favorited":false,"coordinates":null,"in_reply_to_user_id_str":"15764644","entities":{"hashtags":[],"user_mentions":[{"screen_name":"NancyPelosi","id":15764644,"indices":[0,12],"name":"Nancy Pelosi ","id_str":"15764644"}],"urls":[{"display_url":"1.usa.gov/192vMkj","expanded_url":"http://1.usa.gov/192vMkj","indices":[99,121],"url":"http://t.co/BPpE1KddMP"}]},"in_reply_to_user_id":15764644,"source":"web","place":null,"retweet_count":2,"truncated":false,"id":336991330922287104,"retweeted":false,"created_at":"Tue May 21 23:46:08 +0000 2013","contributors":null,"in_reply_to_status_id":null,"text":"@NancyPelosi thank you for your strong words of support for DC's Douglass statue &amp; DC equality http://t.co/BPpE1KddMP","in_reply_to_screen_name":"NancyPelosi","possibly_sensitive":false,"id_str":"336991330922287104","geo":null},"profile_use_background_image":true,"is_translator":false,"profile_background_image_url_https":"https://si0.twimg.com/profile_background_images/266506620/twitpic8.jpg","profile_text_color":"1B23B8","url":"http://www.norton.house.gov","notifications":null,"lang":"en","time_zone":"Indiana (East)","default_profile":false,"followers_count":9486,"statuses_count":642,"profile_sidebar_border_color":"034AA1","location":"Washington, DC","utc_offset":-18000,"profile_image_url_https":"https://si0.twimg.com/profile_images/1178541582/DSC07240_ssp_lo_normal.jpg","friends_count":42,"profile_background_tile":true,"protected":false,"listed_count":659,"description":"Member of the U.S. Congress","geo_enabled":true,"profile_sidebar_fill_color":"8F2B33","following":null,"follow_request_sent":null,"profile_background_color":"023161","profile_image_url":"http://a0.twimg.com/profile_images/1178541582/DSC07240_ssp_lo_normal.jpg","screen_name":"EleanorNorton"}}