{"bioguide_id":"G000556","birthday":"1958-03-13","chamber":"house","contact_form":null,"crp_id":"N00028418","district":9,"facebook_id":null,"fec_ids":["H6FL08213"],"first_name":"Alan","gender":"M","govtrack_id":"412276","in_office":true,"last_name":"Grayson","middle_name":null,"name_suffix":null,"nickname":null,"office":"430 Cannon House Office Building","party":"D","phone":"202-225-9889","state":"FL","state_name":"Florida","thomas_id":"01914","title":"Rep","twitter_id":"AlanGrayson","votesmart_id":68184,"website":"http://grayson.house.gov","youtube_id":"repalangrayson","twitter_id_number":41017380,"twitter_scrape":{"created_at":"Tue May 19 01:00:40 +0000 2009","profile_background_image_url":"http://a0.twimg.com/profile_background_images/391132771/grayson_twitter_bgimage.jpg","name":"Rep. Alan Grayson","contributors_enabled":false,"profile_link_color":"AE2828","default_profile_image":false,"verified":false,"favourites_count":1,"id_str":"41017380","profile_use_background_image":false,"id":41017380,"status":{"favorited":false,"coordinates":null,"in_reply_to_status_id_str":null,"entities":{"hashtags":[],"user_mentions":[],"urls":[{"display_url":"grijalva.house.gov/uploads/Grijal…","expanded_url":"http://grijalva.house.gov/uploads/Grijalva%20Letter%20to%20Obama%20on%20Rejecting%20Keystone%20XL%20May%2023.pdf","indices":[75,97],"url":"http://t.co/n9f1iehiwy"}]},"in_reply_to_user_id":null,"truncated":false,"source":"web","in_reply_to_user_id_str":null,"place":null,"retweet_count":26,"possibly_sensitive":false,"id":337650180998434816,"retweeted":false,"created_at":"Thu May 23 19:24:11 +0000 2013","contributors":null,"in_reply_to_status_id":null,"text":"I signed this letter asking the President to reject the Keystone pipeline. http://t.co/n9f1iehiwy","id_str":"337650180998434816","in_reply_to_screen_name":null,"geo":null},"profile_text_color":"FFFFFF","time_zone":"Eastern Time (US & Canada)","followers_count":42217,"url":null,"notifications":null,"profile_image_url_https":"https://si0.twimg.com/profile_images/1586639544/Screen_Shot_2011-10-13_at_11.43.30_AM_normal.png","lang":"en","profile_sidebar_border_color":"FFFFFF","profile_background_image_url_https":"https://si0.twimg.com/profile_background_images/391132771/grayson_twitter_bgimage.jpg","location":"Orlando, FL","utc_offset":-18000,"default_profile":false,"statuses_count":617,"friends_count":13,"profile_background_tile":false,"is_translator":false,"geo_enabled":false,"profile_sidebar_fill_color":"052639","protected":false,"description":"Representing Florida's 9th district in Congress","listed_count":2179,"following":null,"follow_request_sent":null,"profile_background_color":"132092","profile_image_url":"http://a0.twimg.com/profile_images/1586639544/Screen_Shot_2011-10-13_at_11.43.30_AM_normal.png","screen_name":"AlanGrayson"}}