{"bioguide_id":"B001259","birthday":"1957-10-30","chamber":"house","contact_form":"https://forms.house.gov/braley/webforms/issue_subscribe.html","crp_id":"N00027464","district":1,"facebook_id":"repbrucebraley","fax":"202-225-6666","fec_ids":["H6IA01098"],"first_name":"Bruce","gender":"M","govtrack_id":"412208","in_office":true,"last_name":"Braley","middle_name":"L.","name_suffix":null,"nickname":null,"office":"2263 Rayburn House Office Building","party":"D","phone":"202-225-2911","state":"IA","state_name":"Iowa","thomas_id":"01845","title":"Rep","twitter_id":"brucebraley","votesmart_id":57382,"website":"http://braley.house.gov","youtube_id":"repbrucebraley","twitter_id_number":29293808,"twitter_scrape":{"is_translator":false,"name":"Bruce Braley","time_zone":"Central Time (US & Canada)","follow_request_sent":null,"location":"Iowa & DC","profile_image_url":"http://a0.twimg.com/profile_images/1769228508/71849_10150297480085352_15420665351_15316156_1639358_n_normal.jpg","profile_sidebar_border_color":"050505","id":29293808,"followers_count":14967,"status":{"in_reply_to_status_id":null,"truncated":false,"in_reply_to_screen_name":null,"entities":{"media":[{"url":"http://t.co/uRkhJXqlPM","media_url":"http://pbs.twimg.com/media/BLEG9W0CMAA0vUs.jpg","id":338059098195111936,"media_url_https":"https://pbs.twimg.com/media/BLEG9W0CMAA0vUs.jpg","indices":[88,110],"sizes":{"thumb":{"h":150,"w":150,"resize":"crop"},"medium":{"h":450,"w":600,"resize":"fit"},"small":{"h":255,"w":340,"resize":"fit"},"large":{"h":720,"w":960,"resize":"fit"}},"type":"photo","id_str":"338059098195111936","display_url":"pic.twitter.com/uRkhJXqlPM","source_status_id":null,"expanded_url":"http://twitter.com/BruceBraley/status/338059098190917632/photo/1"}],"urls":[],"hashtags":[],"user_mentions":[]},"geo":null,"source":"<a href=\"http://www.apple.com\" rel=\"nofollow\">Photos on iOS</a>","in_reply_to_status_id_str":null,"place":null,"favorited":false,"possibly_sensitive":false,"coordinates":null,"id":338059098190917632,"in_reply_to_user_id_str":null,"contributors":null,"in_reply_to_user_id":null,"id_str":"338059098190917632","retweet_count":2,"text":"With some of my new friends in Hamilton County at Lomitas Restaurant in Webster County. http://t.co/uRkhJXqlPM","retweeted":false,"created_at":"Fri May 24 22:29:04 +0000 2013"},"profile_background_tile":false,"default_profile_image":false,"profile_sidebar_fill_color":"B3B6C7","geo_enabled":false,"lang":"en","profile_image_url_https":"https://si0.twimg.com/profile_images/1769228508/71849_10150297480085352_15420665351_15316156_1639358_n_normal.jpg","favourites_count":6,"utc_offset":-21600,"screen_name":"BruceBraley","profile_background_color":"DCDADE","created_at":"Mon Apr 06 21:08:54 +0000 2009","profile_background_image_url_https":"https://si0.twimg.com/images/themes/theme6/bg.gif","protected":false,"description":"Listening, Working Hard, and Getting Things Done for the great people of Iowa's First Congressional District","profile_background_image_url":"http://a0.twimg.com/images/themes/theme6/bg.gif","default_profile":false,"following":null,"verified":true,"profile_link_color":"3F5291","contributors_enabled":false,"friends_count":11374,"statuses_count":3936,"id_str":"29293808","profile_use_background_image":false,"profile_text_color":"050505","listed_count":455,"url":null,"notifications":null}}