{"bioguide_id":"S001186","birthday":"1965-10-10","chamber":"house","contact_form":null,"crp_id":"N00031204","district":2,"facebook_id":"RepSteveSoutherland","fax":"202-225-5615","fec_ids":["H0FL02110"],"first_name":"Steve","gender":"M","govtrack_id":"412408","in_office":true,"last_name":"Southerland","middle_name":null,"name_suffix":null,"nickname":null,"office":"1229 Longworth House Office Building","party":"R","phone":"202-225-5235","state":"FL","state_name":"Florida","thomas_id":"02000","title":"Rep","twitter_id":"Rep_Southerland","votesmart_id":124329,"website":"http://southerland.house.gov","youtube_id":"RepSteveSoutherland","twitter_id_number":237781383,"twitter_scrape":{"profile_banner_url":"https://pbs.twimg.com/profile_banners/237781383/1360721382","default_profile_image":false,"created_at":"Thu Jan 13 16:28:13 +0000 2011","name":"Steve Southerland","favourites_count":0,"profile_background_image_url":"http://a0.twimg.com/profile_background_images/797514513/b3c0d0652856fb49c7f02b00bb355fb0.jpeg","contributors_enabled":false,"profile_link_color":"AC0000","verified":true,"id":237781383,"profile_image_url_https":"https://si0.twimg.com/profile_images/1214710606/Capitol_normal.jpg","id_str":"237781383","status":{"in_reply_to_status_id_str":null,"favorited":false,"coordinates":null,"in_reply_to_user_id_str":null,"entities":{"hashtags":[{"indices":[132,138],"text":"FLHD2"}],"user_mentions":[{"screen_name":"AlexHolzbach","id":169742072,"indices":[31,44],"name":"Alex Holzbach","id_str":"169742072"},{"screen_name":"Rep_Southerland","id":237781383,"indices":[85,101],"name":"Steve Southerland","id_str":"237781383"}],"urls":[]},"in_reply_to_user_id":null,"source":"web","place":null,"retweet_count":3,"truncated":false,"id":335486603558518784,"retweeted":false,"created_at":"Fri May 17 20:06:53 +0000 2013","contributors":null,"in_reply_to_status_id":null,"text":"Welcome to the team, Alex! RT: @AlexHolzbach Proud to start my internship today with @Rep_Southerland of Florida's Second District! #FLHD2","in_reply_to_screen_name":null,"id_str":"335486603558518784","geo":null},"profile_use_background_image":true,"profile_background_image_url_https":"https://si0.twimg.com/profile_background_images/797514513/b3c0d0652856fb49c7f02b00bb355fb0.jpeg","profile_text_color":"333333","url":"http://southerland.house.gov","notifications":null,"lang":"en","time_zone":"Central Time (US & Canada)","default_profile":false,"followers_count":4891,"statuses_count":438,"profile_sidebar_border_color":"FFFFFF","location":"U.S. Congress","utc_offset":-21600,"friends_count":513,"profile_background_tile":false,"protected":false,"listed_count":379,"description":"I am privileged to represent Florida's 2nd Congressional District in our fight to shrink government, cut spending, and restore accountability in Congress.","geo_enabled":false,"profile_sidebar_fill_color":"F7F6F0","following":null,"is_translator":false,"follow_request_sent":null,"profile_background_color":"DCDACE","profile_image_url":"http://a0.twimg.com/profile_images/1214710606/Capitol_normal.jpg","screen_name":"Rep_Southerland"}}